[{"anonymous":false,"inputs":[{"indexed":true,"internalType":"uint256","name":"operatorId","type":"uint256"},{"indexed":true,"internalType":"address","name":"ownerAddress","type":"address"},{"indexed":false,"internalType":"bytes","name":"publicKey","type":"bytes"}],"name":"OperatorActivated","type":"event"},{"anonymous":false,"inputs":[{"indexed":true,"internalType":"uint256","name":"operatorId","type":"uint256"},{"indexed":false,"internalType":"string","name":"name","type":"string"},{"indexed":true,"internalType":"address","name":"ownerAddress","type":"address"},{"indexed":false,"internalType":"bytes","name":"publicKey","type":"bytes"}],"name":"OperatorAdded","type":"event"},{"anonymous":false,"inputs":[{"indexed":true,"internalType":"uint256","name":"operatorId","type":"uint256"},{"indexed":true,"internalType":"address","name":"ownerAddress","type":"address"},{"indexed":false,"internalType":"bytes","name":"publicKey","type":"bytes"}],"name":"OperatorDeactivated","type":"event"},{"anonymous":false,"inputs":[{"indexed":true,"internalType":"uint256","name":"operatorId","type":"uint256"},{"indexed":true,"internalType":"address","name":"ownerAddress","type":"address"},{"indexed":false,"internalType":"bytes","name":"publicKey","type":"bytes"},{"indexed":false,"internalType":"uint256","name":"blockNumber","type":"uint256"},{"indexed":false,"internalType":"uint256","name":"fee","type":"uint256"}],"name":"OperatorFeeUpdated","type":"event"},{"anonymous":false,"inputs":[{"indexed":true,"internalType":"uint256","name":"operatorId","type":"uint256"},{"indexed":true,"internalType":"address","name":"ownerAddress","type":"address"},{"indexed":false,"internalType":"bytes","name":"publicKey","type":"bytes"}],"name":"OperatorRemoved","type":"event"},{"anonymous":false,"inputs":[{"indexed":true,"internalType":"uint256","name":"operatorId","type":"uint256"},{"indexed":true,"internalType":"address","name":"ownerAddress","type":"address"},{"indexed":false,"internalType":"bytes","name":"publicKey","type":"bytes"},{"indexed":false,"internalType":"uint256","name":"blockNumber","type":"uint256"},{"indexed":false,"internalType":"uint256","name":"score","type":"uint256"}],"name":"OperatorScoreUpdated","type":"event"},{"anonymous":false,"inputs":[{"indexed":true,"internalType":"address","name":"ownerAddress","type":"address"}],"name":"OwnerValidatorsDisabled","type":"event"},{"anonymous":false,"inputs":[{"indexed":true,"internalType":"address","name":"ownerAddress","type":"address"}],"name":"OwnerValidatorsEnabled","type":"event"},{"anonymous":false,"inputs":[{"indexed":true,"internalType":"address","name":"previousOwner","type":"address"},{"indexed":true,"internalType":"address","name":"newOwner","type":"address"}],"name":"OwnershipTransferred","type":"event"},{"anonymous":false,"inputs":[{"indexed":true,"internalType":"address","name":"ownerAddress","type":"address"},{"indexed":true,"internalType":"bytes","name":"publicKey","type":"bytes"},{"indexed":false,"internalType":"uint256[]","name":"operatorIds","type":"uint256[]"},{"indexed":false,"internalType":"bytes[]","name":"sharesPublicKeys","type":"bytes[]"},{"indexed":false,"internalType":"bytes[]","name":"encryptedKeys","type":"bytes[]"}],"name":"ValidatorAdded","type":"event"},{"anonymous":false,"inputs":[{"indexed":true,"internalType":"address","name":"ownerAddress","type":"address"},{"indexed":false,"internalType":"bytes","name":"publicKey","type":"bytes"}],"name":"ValidatorRemoved","type":"event"},{"anonymous":false,"inputs":[{"indexed":true,"internalType":"address","name":"ownerAddress","type":"address"},{"indexed":true,"internalType":"bytes","name":"publicKey","type":"bytes"},{"indexed":false,"internalType":"uint256[]","name":"operatorIds","type":"uint256[]"},{"indexed":false,"internalType":"bytes[]","name":"sharesPublicKeys","type":"bytes[]"},{"indexed":false,"internalType":"bytes[]","name":"encryptedKeys","type":"bytes[]"}],"name":"ValidatorUpdated","type":"event"},{"inputs":[],"name":"activeValidatorCount","outputs":[{"internalType":"uint256","name":"","type":"uint256"}],"stateMutability":"view","type":"function"},{"inputs":[{"internalType":"address","name":"ownerAddress","type":"address"}],"name":"disableOwnerValidators","outputs":[],"stateMutability":"nonpayable","type":"function"},{"inputs":[{"internalType":"address","name":"ownerAddress","type":"address"}],"name":"enableOwnerValidators","outputs":[],"stateMutability":"nonpayable","type":"function"},{"inputs":[{"internalType":"uint256","name":"operatorId","type":"uint256"}],"name":"getOperatorById","outputs":[{"internalType":"string","name":"","type":"string"},{"internalType":"address","name":"","type":"address"},{"internalType":"bytes","name":"","type":"bytes"},{"internalType":"uint256","name":"","type":"uint256"},{"internalType":"uint256","name":"","type":"uint256"},{"internalType":"uint256","name":"","type":"uint256"},{"internalType":"bool","name":"","type":"bool"}],"stateMutability":"view","type":"function"},{"inputs":[{"internalType":"bytes","name":"publicKey","type":"bytes"}],"name":"getOperatorByPublicKey","outputs":[{"internalType":"string","name":"","type":"string"},{"internalType":"address","name":"","type":"address"},{"internalType":"bytes","name":"","type":"bytes"},{"internalType":"uint256","name":"","type":"uint256"},{"internalType":"uint256","name":"","type":"uint256"},{"internalType":"uint256","name":"","type":"uint256"},{"internalType":"bool","name":"","type":"bool"}],"stateMutability":"view","type":"function"},{"inputs":[{"internalType":"uint256","name":"operatorId","type":"uint256"}],"name":"getOperatorFee","outputs":[{"internalType":"uint256","name":"","type":"uint256"}],"stateMutability":"view","type":"function"},{"inputs":[{"internalType":"uint256","name":"operatorId","type":"uint256"}],"name":"getOperatorOwner","outputs":[{"internalType":"address","name":"","type":"address"}],"stateMutability":"view","type":"function"},{"inputs":[{"internalType":"address","name":"ownerAddress","type":"address"}],"name":"getOperatorsByOwnerAddress","outputs":[{"internalType":"uint256[]","name":"","type":"uint256[]"}],"stateMutability":"view","type":"function"},{"inputs":[{"internalType":"bytes","name":"validatorPublicKey","type":"bytes"}],"name":"getOperatorsByValidator","outputs":[{"internalType":"uint256[]","name":"operatorIds","type":"uint256[]"}],"stateMutability":"view","type":"function"},{"inputs":[],"name":"getRegisteredOperatorsPerAccountLimit","outputs":[{"internalType":"uint256","name":"","type":"uint256"}],"stateMutability":"view","type":"function"},{"inputs":[{"internalType":"bytes","name":"publicKey","type":"bytes"}],"name":"getValidatorOwner","outputs":[{"internalType":"address","name":"","type":"address"}],"stateMutability":"view","type":"function"},{"inputs":[{"internalType":"address","name":"ownerAddress","type":"address"}],"name":"getValidatorsByAddress","outputs":[{"internalType":"bytes[]","name":"","type":"bytes[]"}],"stateMutability":"view","type":"function"},{"inputs":[],"name":"getValidatorsPerOperatorLimit","outputs":[{"internalType":"uint256","name":"","type":"uint256"}],"stateMutability":"view","type":"function"},{"inputs":[{"internalType":"uint256","name":"validatorsPerOperatorLimit_","type":"uint256"},{"internalType":"uint256","name":"registeredOperatorsPerAccountLimit_","type":"uint256"}],"name":"initialize","outputs":[],"stateMutability":"nonpayable","type":"function"},{"inputs":[{"internalType":"address","name":"ownerAddress","type":"address"}],"name":"isLiquidated","outputs":[{"internalType":"bool","name":"","type":"bool"}],"stateMutability":"view","type":"function"},{"inputs":[],"name":"owner","outputs":[{"internalType":"address","name":"","type":"address"}],"stateMutability":"view","type":"function"},{"inputs":[{"internalType":"string","name":"name","type":"string"},{"internalType":"address","name":"ownerAddress","type":"address"},{"internalType":"bytes","name":"publicKey","type":"bytes"},{"internalType":"uint256","name":"fee","type":"uint256"}],"name":"registerOperator","outputs":[{"internalType":"uint256","name":"operatorId","type":"uint256"}],"stateMutability":"nonpayable","type":"function"},{"inputs":[{"internalType":"address","name":"ownerAddress","type":"address"},{"internalType":"bytes","name":"publicKey","type":"bytes"},{"internalType":"uint256[]","name":"operatorIds","type":"uint256[]"},{"internalType":"bytes[]","name":"sharesPublicKeys","type":"bytes[]"},{"internalType":"bytes[]","name":"encryptedKeys","type":"bytes[]"}],"name":"registerValidator","outputs":[],"stateMutability":"nonpayable","type":"function"},{"inputs":[],"name":"registeredOperatorsPerAccountLimit","outputs":[{"internalType":"uint256","name":"","type":"uint256"}],"stateMutability":"view","type":"function"},{"inputs":[{"internalType":"uint256","name":"operatorId","type":"uint256"}],"name":"removeOperator","outputs":[],"stateMutability":"nonpayable","type":"function"},{"inputs":[{"internalType":"bytes","name":"publicKey","type":"bytes"}],"name":"removeValidator","outputs":[],"stateMutability":"nonpayable","type":"function"},{"inputs":[],"name":"renounceOwnership","outputs":[],"stateMutability":"nonpayable","type":"function"},{"inputs":[{"internalType":"address","name":"newOwner","type":"address"}],"name":"transferOwnership","outputs":[],"stateMutability":"nonpayable","type":"function"},{"inputs":[{"internalType":"uint256","name":"operatorId","type":"uint256"},{"internalType":"uint256","name":"fee","type":"uint256"}],"name":"updateOperatorFee","outputs":[],"stateMutability":"nonpayable","type":"function"},{"inputs":[{"internalType":"uint256","name":"operatorId","type":"uint256"},{"internalType":"uint256","name":"score","type":"uint256"}],"name":"updateOperatorScore","outputs":[],"stateMutability":"nonpayable","type":"function"},{"inputs":[{"internalType":"uint256","name":"_registeredOperatorsPerAccountLimit","type":"uint256"}],"name":"updateRegisteredOperatorsPerAccountLimit","outputs":[],"stateMutability":"nonpayable","type":"function"},{"inputs":[{"internalType":"bytes","name":"publicKey","type":"bytes"},{"internalType":"uint256[]","name":"operatorIds","type":"uint256[]"},{"internalType":"bytes[]","name":"sharesPublicKeys","type":"bytes[]"},{"internalType":"bytes[]","name":"encryptedKeys","type":"bytes[]"}],"name":"updateValidator","outputs":[],"stateMutability":"nonpayable","type":"function"},{"inputs":[{"internalType":"uint256","name":"_validatorsPerOperatorLimit","type":"uint256"}],"name":"updateValidatorsPerOperatorLimit","outputs":[],"stateMutability":"nonpayable","type":"function"},{"inputs":[{"internalType":"bytes","name":"publicKey","type":"bytes"}],"name":"validators","outputs":[{"internalType":"address","name":"","type":"address"},{"internalType":"bytes","name":"","type":"bytes"},{"internalType":"bool","name":"","type":"bool"}],"stateMutability":"view","type":"function"},{"inputs":[{"internalType":"uint256","name":"operatorId","type":"uint256"}],"name":"validatorsPerOperatorCount","outputs":[{"internalType":"uint256","name":"","type":"uint256"}],"stateMutability":"view","type":"function"},{"inputs":[],"name":"validatorsPerOperatorLimit","outputs":[{"internalType":"uint256","name":"","type":"uint256"}],"stateMutability":"view","type":"function"}]